README.rst
setup.py
tinyhttp/__init__.py
tinyhttp/__main__.py
tinyhttp/helper.py
tinyhttp/tcp.py
tinyhttp.egg-info/PKG-INFO
tinyhttp.egg-info/SOURCES.txt
tinyhttp.egg-info/dependency_links.txt
tinyhttp.egg-info/entry_points.txt
tinyhttp.egg-info/top_level.txt
tinyhttp/asynchronous/__init__.py
tinyhttp/asynchronous/__main__.py
tinyhttp/asynchronous/asyncserver.py
tinyhttp/http/__init__.py
tinyhttp/http/server.py
tinyhttp/thread/__init__.py
tinyhttp/thread/__main__.py
tinyhttp/thread/threadserver.py