Metadata-Version: 1.0
Name: tinyhttp
Version: 1.1.0
Summary: Async static HTTP server.
Home-page: https://github.com/WincerChan/Tiny-Http
Author: Wincer
Author-email: UNKNOWN
License: GPL-3.0
Platform: UNKNOWN
